pygdst/__init__.py
pygdst/convert.py
pygdst/example.py
pygdst/gdst.py
pygdst/paras.py
pygdst-0.1.1.dist-info/licenses/LICENSE
pygdst-0.1.1.dist-info/METADATA
pygdst-0.1.1.dist-info/WHEEL
pygdst-0.1.1.dist-info/top_level.txt
pygdst-0.1.1.dist-info/RECORD
