Metadata-Version: 2.4
Name: pygdst
Version: 0.1.1
Summary: A toolkit to read and convert seismic data of GDST (https://www.geodeepsensing.com/) sensors to H5 and SAC file format 
Author-email: Shi Yongxiang <shi@mail.iggcas.ac.cn>
Project-URL: Homepage, https://gitee.com/luckyshiOVO/pygdst
Project-URL: Issues, https://gitee.com/luckyshiOVO/pygdst/issues
Classifier: Programming Language :: Python :: 3
Classifier: License :: OSI Approved :: MIT License
Classifier: Operating System :: OS Independent
Requires-Python: >=3.7
License-File: LICENSE
Dynamic: license-file
